class ObjCall {
    
    void CallMethod(){
        ObjCall oc = new ObjCall();
        oc.CallMe();
    }
    
    public void CallMe(){}
}

AST:
Just 
	[Class 
	(Identifier "ObjCall") 
	[] 
	[Method {
		getIdentifier = Identifier "CallMethod", 
		getMods = [], 
		getReturnType = JVoid, 
		getParamList = [], 
		getBody = 
			Just 
				(Block 
				[LocalVar 
					(VarDecl {
						getIdentifier = Identifier "oc", 
						getMods = [], 
						getType = RefType 
							(Name {
								path = [], 
								getIdentifier = Identifier "ObjCall"}), 
						getRHS = 
							Just 
								(ExprExprStmt 
									(Instantiation 
										(Name {
											path = [], 
											getIdentifier = Identifier "ObjCall"}) 
									[]))}),
					StmtExprStmt 
						(Apply 
							(Iden 
								(Name {
									path = 
									[Identifier "oc"], 
									getIdentifier = Identifier "CallMe"})) 
							[])])},
	Method {
		getIdentifier = Identifier "CallMe", 
		getMods = [Public], 
		getReturnType = JVoid, 
		getParamList = [], 
		getBody = Just (Block [])}]]
		
		
TAST:
Just 
	[Class 
	(Identifier "ObjCall") 
	[] 
	[Method {
		getIdentifier = Identifier "CallMethod", 
		getMods = [], 
		getReturnType = JVoid, 
		getParamList = [], 
		getBody =
			Just 
				(TypedStatement (Block 
				[(TypedStatement (LocalVar 
					(VarDecl {
						getIdentifier = Identifier "oc", 
						getMods = [], 
						getType = RefType 
							(Name {
								path = [], 
								getIdentifier = Identifier "ObjCall"}), 
						getRHS = 
							Just 
								(TypedExpression (ExprExprStmt 
									(TypedStatementExpression (Instantiation 
										(Name {
											path = [], 
											getIdentifier = Identifier "ObjCall"}) 
									[]), RefType "ObjCall")),  RefType "ObjCall")})), RefType "ObjCall"),
					(TypedStatement StmtExprStmt 
						(TypedStatementExpression (Apply 
							(Iden 
								(Name {
									path = 
									[Identifier "oc"], 
									getIdentifier = Identifier "CallMe"})) 
							[]), JVoid),  JVoid)]),  JVoid)},
	Method {
		getIdentifier = Identifier "CallMe", 
		getMods = [Public], 
		getReturnType = JVoid, 
		getParamList = [], 
		getBody = Just (TypedStatement (Block []), JVoid)}]]

jvmabyte:
magic = 0x CAFEBABE
minor_version = 0
major_version = 52
constant_pool_count = 18
constant_pool =
{
1| tag = CONSTANT_Methodref, class_index = 5, name_and_type_index = 14
2| tag = CONSTANT_Class, name_index = 15
3| tag = CONSTANT_Methodref, class_index = 2, name_and_type_index = 14
4| tag = CONSTANT_Methodref, class_index = 2, name_and_type_index = 16
5| tag = CONSTANT_Class, name_index = 17
6| tag = CONSTANT_Utf8, length = 6, bytes = <init>
7| tag = CONSTANT_Utf8, length = 3, bytes = ()V
8| tag = CONSTANT_Utf8, length = 4, bytes = Code
9| tag = CONSTANT_Utf8, length = 15, bytes = LineNumberTable
10| tag = CONSTANT_Utf8, length = 10, bytes = CallMethod
11| tag = CONSTANT_Utf8, length = 6, bytes = CallMe
12| tag = CONSTANT_Utf8, length = 10, bytes = SourceFile
13| tag = CONSTANT_Utf8, length = 21, bytes = ObjectMethodCall.java
14| tag = CONSTANT_NameAndType, name_index = 6, descriptor_index = 7
15| tag = CONSTANT_Utf8, length = 7, bytes = ObjCall
16| tag = CONSTANT_NameAndType, name_index = 11, descriptor_index = 7
17| tag = CONSTANT_Utf8, length = 16, bytes = java/lang/Object
}
access_flags = 32  // ACC_SUPER
this_class = #2  // ObjCall
super_class = #5  // java/lang/Object
interfaces_count = 0
interfaces = {}
fields_count = 0
fields = {}
methods_count = 3
methods [0] =
{
access_flags = 0
name_index = #6  // <init>
descriptor_index = #7  // ()V
attributes_count = 1
attributes [0] =
{
attribute_name_index = #8  // Code
attribute_length = 29
max_stack = 1, max_locals = 1
code_length = 5
code =
{
    0  aload_0
    1  invokespecial #1  // java/lang/Object.<init> ()V
    4  return
}
exception_table_length = 0
exception_table = {}
attributes_count = 1
attributes [0] =
{
attribute_name_index = #9  // LineNumberTable
attribute_length = 6
line_number_table_length = 1
line_number_table =
{
start_pc, line_number
0| 0, 1
}
}
}
}
methods [1] =
{
access_flags = 0
name_index = #10  // CallMethod
descriptor_index = #7  // ()V
attributes_count = 1
attributes [0] =
{
attribute_name_index = #8  // Code
attribute_length = 45
max_stack = 2, max_locals = 2
code_length = 13
code =
{
    0  new #2  // ObjCall
    3  dup
    4  invokespecial #3  // ObjCall.<init> ()V
    7  astore_1
    8  aload_1
    9  invokevirtual #4  // ObjCall.CallMe ()V
   12  return
}
exception_table_length = 0
exception_table = {}
attributes_count = 1
attributes [0] =
{
attribute_name_index = #9  // LineNumberTable
attribute_length = 14
line_number_table_length = 3
line_number_table =
{
start_pc, line_number
0| 0, 4
1| 8, 5
2| 12, 6
}
}
}
}
methods [2] =
{
access_flags = 1  // ACC_PUBLIC
name_index = #11  // CallMe
descriptor_index = #7  // ()V
attributes_count = 1
attributes [0] =
{
attribute_name_index = #8  // Code
attribute_length = 25
max_stack = 0, max_locals = 1
code_length = 1
code =
{
    0  return
}
exception_table_length = 0
exception_table = {}
attributes_count = 1
attributes [0] =
{
attribute_name_index = #9  // LineNumberTable
attribute_length = 6
line_number_table_length = 1
line_number_table =
{
start_pc, line_number
0| 0, 8
}
}
}
}
attributes_count = 1
attributes [0] =
{
attribute_name_index = #12  // SourceFile
attribute_length = 2
sourcefile_index = #13  // ObjectMethodCall.java
}